ZiyudaShujuZhiSparkRumenjiaochengScalaBanFix1/README.md
ZiyudaShujuZhiSparkRumenjiaochengScalaBanFix1/__init__.py
ZiyudaShujuZhiSparkRumenjiaochengScalaBanFix1/__main__.py
ZiyudaShujuZhiSparkRumenjiaochengScalaBanFix1/file.epub
ZiyudaShujuZhiSparkRumenjiaochengScalaBanFix1/index.html
ZiyudaShujuZhiSparkRumenjiaochengScalaBanFix1/css/__init__.py
ZiyudaShujuZhiSparkRumenjiaochengScalaBanFix1/css/annotations.css
ZiyudaShujuZhiSparkRumenjiaochengScalaBanFix1/css/main.css
ZiyudaShujuZhiSparkRumenjiaochengScalaBanFix1/css/normalize.css
ZiyudaShujuZhiSparkRumenjiaochengScalaBanFix1/css/popup.css
ZiyudaShujuZhiSparkRumenjiaochengScalaBanFix1/font/__init__.py
ZiyudaShujuZhiSparkRumenjiaochengScalaBanFix1/font/fontello.eot
ZiyudaShujuZhiSparkRumenjiaochengScalaBanFix1/font/fontello.svg
ZiyudaShujuZhiSparkRumenjiaochengScalaBanFix1/font/fontello.ttf
ZiyudaShujuZhiSparkRumenjiaochengScalaBanFix1/font/fontello.woff
ZiyudaShujuZhiSparkRumenjiaochengScalaBanFix1/img/__init__.py
ZiyudaShujuZhiSparkRumenjiaochengScalaBanFix1/img/annotator-glyph-sprite.png
ZiyudaShujuZhiSparkRumenjiaochengScalaBanFix1/img/annotator-icon-sprite.png
ZiyudaShujuZhiSparkRumenjiaochengScalaBanFix1/img/apple-touch-icon.png
ZiyudaShujuZhiSparkRumenjiaochengScalaBanFix1/img/cancelfullscreen.png
ZiyudaShujuZhiSparkRumenjiaochengScalaBanFix1/img/close.png
ZiyudaShujuZhiSparkRumenjiaochengScalaBanFix1/img/fullscreen.png
ZiyudaShujuZhiSparkRumenjiaochengScalaBanFix1/img/loader.gif
ZiyudaShujuZhiSparkRumenjiaochengScalaBanFix1/img/menu-icon.png
ZiyudaShujuZhiSparkRumenjiaochengScalaBanFix1/img/save.png
ZiyudaShujuZhiSparkRumenjiaochengScalaBanFix1/img/saved.png
ZiyudaShujuZhiSparkRumenjiaochengScalaBanFix1/img/settings-s.png
ZiyudaShujuZhiSparkRumenjiaochengScalaBanFix1/img/settings.png
ZiyudaShujuZhiSparkRumenjiaochengScalaBanFix1/img/star.png
ZiyudaShujuZhiSparkRumenjiaochengScalaBanFix1/js/__init__.py
ZiyudaShujuZhiSparkRumenjiaochengScalaBanFix1/js/epub.js
ziyuda_shuju_zhi_spark_rumenjiaocheng_scala_ban_fix1-2025.3.24.1.dist-info/METADATA
ziyuda_shuju_zhi_spark_rumenjiaocheng_scala_ban_fix1-2025.3.24.1.dist-info/WHEEL
ziyuda_shuju_zhi_spark_rumenjiaocheng_scala_ban_fix1-2025.3.24.1.dist-info/entry_points.txt
ziyuda_shuju_zhi_spark_rumenjiaocheng_scala_ban_fix1-2025.3.24.1.dist-info/top_level.txt
ziyuda_shuju_zhi_spark_rumenjiaocheng_scala_ban_fix1-2025.3.24.1.dist-info/RECORD
